diesis/Config.py
diesis/Converter.py
diesis/FileScanner.py
diesis/Logger.py
diesis/LyricsFinder.py
diesis/Song.py
diesis/TagHelper.py
diesis/Utils.py
diesis/__init__.py
diesis/main.py
diesis/scrapers/AZLyrics.py
diesis/scrapers/LyricsScraper.py
diesis/scrapers/MusixMatch.py
diesis/scrapers/__init__.py
Diesis-1.0.5.dist-info/LICENSE.txt
Diesis-1.0.5.dist-info/METADATA
Diesis-1.0.5.dist-info/WHEEL
Diesis-1.0.5.dist-info/entry_points.txt
Diesis-1.0.5.dist-info/top_level.txt
Diesis-1.0.5.dist-info/RECORD
