Metadata-Version: 2.1
Name: Diesis
Version: 1.0.5
Summary: A simple auto-tagging tool for precise music collectors.
Home-page: https://github.com/RyanJ93/diesis
Author: Enrico Sola
Author-email: info@enricosola.com
License: MIT
Keywords: music,tagging,id3,mp3,m4a,flac,ogg
Platform: UNKNOWN
Classifier: Development Status :: 3 - Alpha
Classifier: Intended Audience :: Developers
Classifier: Topic :: Software Development :: Build Tools
Classifier: License :: OSI Approved :: MIT License
Classifier: Programming Language :: Python :: 3.5
Classifier: Programming Language :: Python :: 3.6
Classifier: Programming Language :: Python :: 3.7
Requires-Python: >=3.5
Requires-Dist: mutagen
Requires-Dist: beautifulsoup4
Requires-Dist: pydub
